{"callee_method_names":[],"method_name":"AFPChain.setAlgorithmName","method_implementation":"{\n    this.algorithmName = algorithmName;\n}","repo_id":"9","comment":"/**\n * Caution has to be made when changing the algorithmName of an AFPChain,\n * since downstream analysis methods (scores, display, etc) behave\n * differently if the alignment is flexible (created with FatCat).\n *\n * @param algorithmName\n */\n","repo_name":"biojava-master/","id":502,"method_signature":"void setAlgorithmName(String)"}