{"callee_method_names":[],"method_name":"AFPChain.setDistanceMatrix","method_implementation":"{\n    this.distanceMatrix = distanceMatrix;\n    //System.out.println(\"Setting distMatrix \"+(distanceMatrix==null?\"null\":\"not null\"));\n}","repo_id":"9","comment":"/**\n * A matrix with <i>ca1length<\/i> rows and <i>ca2length<\/i> columns.\n * For CE this is the distance matrix, but the exact interpretation is left\n * up to the alignment algorithm.\n * @param distanceMatrix A matrix with dimensions ca1length x ca2length\n */\n","repo_name":"biojava-master/","id":506,"method_signature":"void setDistanceMatrix(Matrix)"}