{"callee_method_names":["SequenceAsStringHelper<C>.getSequenceAsString"],"method_name":"ArrayListSequenceReader.getSequenceAsString","method_implementation":"{\n    // TODO Optimise/cache.\n    SequenceAsStringHelper<C> sequenceAsStringHelper = new SequenceAsStringHelper<C>();\n    return sequenceAsStringHelper.getSequenceAsString(this.parsedCompounds, compoundSet, begin, end, strand);\n}","repo_id":"9","comment":"/**\n * @param begin\n * @param end\n * @param strand\n * @return\n */\n","repo_name":"biojava-master/","id":2960,"method_signature":"String getSequenceAsString(Integer, Integer, Strand)"}