{"callee_method_names":["GeneChromosomePosition.getOrientation"],"method_name":"ChromosomeMappingTools.getCDSExonRanges","method_implementation":"{\n    if (chromPos.getOrientation() == '+')\n        return getCDSExonRangesForward(chromPos, CDS);\n    return getCDSExonRangesReverse(chromPos, CDS);\n}","repo_id":"9","comment":"/**\n * Extracts the exon boundaries in CDS coordinates. (needs to be divided by 3 to get AA positions)\n *\n * @param chromPos\n * @return\n */\n","repo_name":"biojava-master/","id":2485,"method_signature":"List<Range<Integer>> getCDSExonRanges(GeneChromosomePosition)"}