{"callee_method_names":["String.isEmpty","Pattern.matcher","Matcher.matches","Matcher.group","Logger.debug","Logger.debug","List<EcodDomain>.size","String.equals","double[].getDomainId"],"method_name":"EcodInstallation.getDomainsById","method_implementation":"{\n    if (ecodId == null || ecodId.isEmpty()) {\n        return null;\n    }\n    Matcher match = ECOD_RE.matcher(ecodId);\n    String pdbId = null;\n    if (match.matches())\n        pdbId = match.group(1);\n    List<EcodDomain> doms = getDomainsForPdb(pdbId);\n    if (doms == null) {\n        logger.debug(\"Null domains for {} from {}\", pdbId, ecodId);\n        return null;\n    }\n    logger.debug(\"Got {} domains from {}\", doms.size(), pdbId);\n    for (EcodDomain d : doms) {\n        if (ecodId.equals(d.getDomainId())) {\n            return d;\n        }\n    }\n    return null;\n}","repo_id":"9","comment":"/**\n * Get a particular ECOD domain by the domain ID (e.g. \"e4hhbA1\")\n * @param ecodId\n * @return\n * @throws IOException\n */\n","repo_name":"biojava-master/","id":1803,"method_signature":"EcodDomain getDomainsById(String)"}