{"callee_method_names":[],"method_name":"GenericGenbankHeaderParser.setVersion","method_implementation":"{\n    if (this.versionSeen)\n        throw new ParserException(\"Current BioEntry already has a version\");\n    else {\n        try {\n            this.version = version;\n            this.versionSeen = true;\n        } catch (NumberFormatException e) {\n            throw new ParserException(\"Could not parse version as an integer\");\n        }\n    }\n}","repo_id":"9","comment":"/**\n * {@inheritDoc}\n * The last accession passed to this routine will always be the one used.\n */\n","repo_name":"biojava-master/","id":2831,"method_signature":"void setVersion(int)"}