{"callee_method_names":["NavigableMap<Double, Color>.remove"],"method_name":"GradientMapper.remove","method_implementation":"{\n    if (((Double) position).isInfinite()) {\n        throw new UnsupportedOperationException(\"Cannot remove infinite endpoints\");\n    }\n    return mapping.remove(position);\n}","repo_id":"9","comment":"/**\n * @param position\n * @return\n * @see java.util.Map#remove(java.lang.Object)\n */\n","repo_name":"biojava-master/","id":3358,"method_signature":"Color remove(Object)"}