{"callee_method_names":["List<S>.size","List<S>.size","List<PairwiseSequenceScorer<S, C>>.get","List<PairwiseSequenceScorer<S, C>>.get"],"method_name":"GuideTree.getScoreMatrix","method_implementation":"{\n    double[][] matrix = new double[sequences.size()][sequences.size()];\n    for (int i = 0, n = 0; i < matrix.length; i++) {\n        matrix[i][i] = scorers.get(i).getMaxScore();\n        for (int j = i + 1; j < matrix.length; j++) {\n            matrix[i][j] = matrix[j][i] = scorers.get(n++).getScore();\n        }\n    }\n    return matrix;\n}","repo_id":"9","comment":"/**\n * Returns the similarity matrix used to construct this guide tree.  The scores have not been normalized.\n *\n * @return the similarity matrix used to construct this guide tree\n */\n","repo_name":"biojava-master/","id":10,"method_signature":"double[][] getScoreMatrix()"}