{"callee_method_ids":[995],"callee_method_names":["HetatomImpl.setResidueNumber","HetatomImpl.getResidueNumber"],"method_name":"HetatomImplTest.testSetGetResidueNumber","method_implementation":"{\n    //        System.out.println(\"setGetResidueNumber\");\n    ResidueNumber residueNumber = new ResidueNumber(\"A\", 42, ' ');\n    HetatomImpl instance = new HetatomImpl();\n    instance.setResidueNumber(residueNumber);\n    ResidueNumber expResult = residueNumber;\n    ResidueNumber result = instance.getResidueNumber();\n    Assert.assertEquals(expResult, result);\n}","repo_id":"9","comment":"/**\n * Test of getSeqNum method, of class HetatomImpl.\n */\n","repo_name":"biojava-master/","id":2169,"method_signature":"void testSetGetResidueNumber()"}