{"callee_method_names":["BetaBridge.equals","BetaBridge.equals","Logger.info"],"method_name":"SecStrucState.addBridge","method_implementation":"{\n    if (bridge1 == null) {\n        bridge1 = bridge;\n        return true;\n    } else if (bridge1.equals(bridge)) {\n        return true;\n    } else if (bridge2 == null) {\n        bridge2 = bridge;\n        return true;\n    } else if (bridge2.equals(bridge)) {\n        return true;\n    } else {\n        //no space left, cannot add the bridge\n        logger.info(\"Residue forms more than 2 beta Bridges, \" + \"DSSP output might differ in Bridges column.\");\n        return false;\n    }\n}","repo_id":"9","comment":"/**\n * Adds a Bridge to the residue. Each residue can only store two bridges. If\n * the residue contains already two Bridges, the Bridge will not be added\n * and the method returns false.\n *\n * @param bridge\n * @return false if the Bridge was not added, true otherwise\n */\n","repo_name":"biojava-master/","id":1587,"method_signature":"boolean addBridge(BetaBridge)"}