{"callee_method_ids":[929,937],"callee_method_names":["Grid.addAtoms","Grid.getAtomContacts"],"method_name":"StructureTools.getAtomsCAInContact","method_implementation":"{\n    Grid grid = new Grid(cutoff);\n    Atom[] atoms = getAtomCAArray(chain);\n    grid.addAtoms(atoms);\n    return grid.getAtomContacts();\n}","repo_id":"9","comment":"/**\n * Returns the set of intra-chain contacts for the given chain for C-alpha\n * atoms (including non-standard aminoacids appearing as HETATM groups),\n * i.e. the contact map. Uses a spatial hashing algorithm that speeds up\n * the calculation without need of full distance matrix. The parsing mode\n * {@link FileParsingParameters#setAlignSeqRes(boolean)} needs to be set to\n * true for this to work.\n *\n * @param chain\n * @param cutoff\n * @return\n * @see #getRepresentativeAtomsInContact(Chain, double)\n */\n","repo_name":"biojava-master/","id":1049,"method_signature":"AtomContactSet getAtomsCAInContact(Chain, double)"}