{"callee_method_ids":[3784,3795,3789,3811],"callee_method_names":["SurvFitKM.process","JFrame.setDefaultCloseOperation","JFrame.add","KaplanMeierFigure.setSize","JFrame.setSize","JFrame.setVisible","ArrayList<String>.add","ArrayList<String>.add","KaplanMeierFigure.setSurvivalData","KaplanMeierFigure.setFigureLineInfo","KaplanMeierFigure.savePNG","double[][].printStackTrace"],"method_name":"SurvFitKM.main","method_implementation":"{\n    // TODO code application logic here\n    try {\n        String datafile = \"/Users/Scooter/scripps/ngs/BLJ/E2197/Predictive Signatures/V$HSF_Q6-E2197 TTR.txt\";\n        SurvFitKM survFitKM = new SurvFitKM();\n        SurvFitInfo si = survFitKM.process(datafile, \"TIME\", \"STATUS\", \"WEIGHT\", \"MEAN\", true);\n        if (true) {\n            KaplanMeierFigure kaplanMeierFigure = new KaplanMeierFigure();\n            JFrame application = new JFrame();\n            application.setDefaultCloseOperation(JFrame.EXIT_ON_CLOSE);\n            application.add(kaplanMeierFigure);\n            kaplanMeierFigure.setSize(500, 400);\n            // window is 500 pixels wide, 400 high\n            application.setSize(500, 400);\n            application.setVisible(true);\n            ArrayList<String> titles = new ArrayList<String>();\n            titles.add(\"Line 1\");\n            titles.add(\"line 2\");\n            kaplanMeierFigure.setSurvivalData(titles, si, null);\n            ArrayList<String> figureInfo = new ArrayList<String>();\n            //   figureInfo.add(\"HR=2.1 95% CI(1.8-2.5)\");\n            //   figureInfo.add(\"p-value=.001\");\n            kaplanMeierFigure.setFigureLineInfo(figureInfo);\n            kaplanMeierFigure.savePNG(\"/Users/Scooter/Downloads/test.png\");\n        }\n    } catch (Exception e) {\n        e.printStackTrace();\n    }\n}","repo_id":"9","comment":"/**\n * @param args the command line arguments\n */\n","repo_name":"biojava-master/","id":3785,"method_signature":"void main(String[])"}