{"callee_method_names":["List<C>.add","CompoundSet<C>.getCompoundForString","List<C>.add","CompoundSet<C>.getCompoundForString","List<C>.add","CompoundSet<C>.getCompoundForString","List<C>.add","CompoundSet<C>.getCompoundForString"],"method_name":"TwoBitArrayWorker.generateIndexToCompounds","method_implementation":"{\n    CompoundSet<C> cs = getCompoundSet();\n    List<C> result = new ArrayList<C>();\n    result.add(cs.getCompoundForString(\"T\"));\n    result.add(cs.getCompoundForString(\"C\"));\n    result.add(cs.getCompoundForString(\"A\"));\n    result.add(cs.getCompoundForString(\"G\"));\n    return result;\n}","repo_id":"9","comment":"/**\n * Returns a List which encodes TCAG into positions 0,1,2,3.\n */\n","repo_name":"biojava-master/","id":2978,"method_signature":"List<C> generateIndexToCompounds()"}