{"callee_method_names":[],"method_name":"TwoBitParser.close","method_implementation":"{\n    cur_seq_name = null;\n    cur_nn_blocks = null;\n    cur_mask_blocks = null;\n    cur_seq_pos = -1;\n    cur_dna_size = -1;\n    cur_nn_block_num = -1;\n    cur_mask_block_num = -1;\n    cur_bits = null;\n    buffer_size = 0;\n    buffer_pos = -1;\n    file_pos = -1;\n    start_file_pos = -1;\n}","repo_id":"9","comment":"/**\n * Method closes current sequence and it's necessary to invoke it before setting\n * new current sequence.\n */\n","repo_name":"biojava-master/","id":2385,"method_signature":"void close()"}